ChangeLog
LICENSE.txt
README.txt
TODO
setup.py
pybktools/__init__.py
pybktools/pybktools.txt
pybktools/test.py
pybktools.egg-info/PKG-INFO
pybktools.egg-info/SOURCES.txt
pybktools.egg-info/dependency_links.txt
pybktools.egg-info/requires.txt
pybktools.egg-info/top_level.txt
pybktools/tmpl/MOA-ID-AUTH-GetAuthenticationData-REQUEST.txt
pybktools/tmpl/MOA-ID-AUTH-GetAuthenticationData-REQUEST.xml
pybktools/tmpl/MOA-ID-AUTH-GetAuthenticationData-RESPONSE.xml
pybktools/tmpl/MOA-SP-VerifySignatureRequest.xml
pybktools/tmpl/SIGN-CreateXMLSignatureREQUEST.xml