Metadata-Version: 1.0
Name: pybktools
Version: 0.0.1
Summary: Providing Python support for the Austrian Buergerkarte.
Home-page: UNKNOWN
Author: Hermann Himmelbauer
Author-email: dusty@qwer.tk
License: LGPL
Platform: UNKNOWN
